rossml/__init__.py
rossml/pipeline.py
rossml/random_sampler.py
ross_ml-0.0.1.dist-info/LICENSE.md
ross_ml-0.0.1.dist-info/METADATA
ross_ml-0.0.1.dist-info/WHEEL
ross_ml-0.0.1.dist-info/top_level.txt
ross_ml-0.0.1.dist-info/RECORD
