Metadata-Version: 2.1
Name: ross-ml
Version: 0.0.1
Summary: ross-machine-learning
Home-page: https://github.com/ross-rotordynamics/ross-ml
Author: ROSS developers
Author-email: raphaelts@gmail.com
License: MIT
Platform: UNKNOWN
Classifier: License :: OSI Approved :: MIT License
Classifier: Programming Language :: Python
Classifier: Programming Language :: Python :: 3
Classifier: Programming Language :: Python :: 3.6
Classifier: Programming Language :: Python :: Implementation :: CPython
Requires-Python: >=3.6.0
Requires-Dist: numpy
Requires-Dist: scipy
Requires-Dist: pandas (>=0.23)
Requires-Dist: plotly (>=4.7.0)
Requires-Dist: statsmodels
Requires-Dist: sklearn
Requires-Dist: tensorflow
Provides-Extra: dev
Requires-Dist: pytest (>=4.6) ; extra == 'dev'
Requires-Dist: pytest-cov ; extra == 'dev'
Requires-Dist: coverage ; extra == 'dev'
Requires-Dist: codecov ; extra == 'dev'
Requires-Dist: sphinx ; extra == 'dev'
Requires-Dist: sphinx-bootstrap-theme ; extra == 'dev'
Requires-Dist: nbsphinx ; extra == 'dev'
Requires-Dist: numpydoc ; extra == 'dev'
Requires-Dist: sphinxcontrib-bibtex ; extra == 'dev'
Requires-Dist: isort ; extra == 'dev'
